msbuild_mcp_server/server.py
msbuild_mcp_server-0.1.2.dist-info/licenses/LICENSE
msbuild_mcp_server-0.1.2.dist-info/METADATA
msbuild_mcp_server-0.1.2.dist-info/WHEEL
msbuild_mcp_server-0.1.2.dist-info/entry_points.txt
msbuild_mcp_server-0.1.2.dist-info/top_level.txt
msbuild_mcp_server-0.1.2.dist-info/RECORD
