Metadata-Version: 2.4
Name: msbuild-mcp-server
Version: 0.1.2
Summary: A lightweight MCP server for automating MSBuild projects and solutions builds.
License: MIT
Requires-Python: >=3.11
License-File: LICENSE
Requires-Dist: fastmcp>=2.0
Requires-Dist: uv
Requires-Dist: vswhere>=1.0.0
Requires-Dist: pydantic>=2.0.0
Provides-Extra: dev
Requires-Dist: pytest; extra == "dev"
Dynamic: license-file
